aphantasist/__init__.py
aphantasist/__main__.py
aphantasist/core/config.py
aphantasist/core/config_files.py
aphantasist/core/default_files/config.yaml
aphantasist/core/default_files/mail_folders.yaml
aphantasist/modules/img2txt.py
aphantasist-0.1.0.dist-info/WHEEL
aphantasist-0.1.0.dist-info/entry_points.txt
aphantasist-0.1.0.dist-info/METADATA
aphantasist-0.1.0.dist-info/RECORD
