Metadata-Version: 2.4
Name: aphantasist
Version: 0.1.0
Summary: 💭 Aphantasist is an simple OCR that uses EasyOCR to read images from a folder and paste the texts in another.
Author: Cesar Cardoso
Author-email: Cesar Cardoso <hello@cesarcardoso.cc>
License-Expression: MIT
Requires-Dist: easyocr>=1.7.2
Requires-Dist: pillow>=12.1.0
Requires-Python: >=3.11
